object_print/__init__.py
object_print-0.1.0.dist-info/METADATA
object_print-0.1.0.dist-info/WHEEL
object_print-0.1.0.dist-info/RECORD
