Metadata-Version: 2.1
Name: object-print
Version: 0.1.0
Summary: Pretty-printer that works a little differently from `pprint`.
Home-page: https://github.com/vtbassmatt/object-print
License: MIT
Author: Matt Cooper
Author-email: vtbassmatt@gmail.com
Requires-Python: >=3.11,<4.0
Classifier: Environment :: Console
Classifier: Intended Audience :: Developers
Classifier: License :: OSI Approved :: MIT License
Classifier: Programming Language :: Python
Classifier: Programming Language :: Python :: 3
Classifier: Programming Language :: Python :: 3.11
Classifier: Topic :: Software Development
Project-URL: Repository, https://github.com/vtbassmatt/object-print.git
